planetext_table/__init__.py
planetext_table/gen.py
planetext_table/normalized_list.py
tests/__init__.py
tests/test_gen.py
tests/test_normalized_list.py
planetext_table-0.1.0.dist-info/LICENSE
planetext_table-0.1.0.dist-info/METADATA
planetext_table-0.1.0.dist-info/WHEEL
planetext_table-0.1.0.dist-info/top_level.txt
planetext_table-0.1.0.dist-info/RECORD
