Metadata-Version: 2.1
Name: planetext-table
Version: 0.1.0
Summary: planetext table generator
Home-page: https://github.com/bugph0bia/planetext-table
Author: bugph0bia
Author-email: 
License: MIT
Platform: UNKNOWN
Classifier: Topic :: Text Processing :: General
Classifier: Topic :: Software Development :: Libraries :: Python Modules
Classifier: Programming Language :: Python :: 3 :: Only
Classifier: License :: OSI Approved :: MIT License
Classifier: Intended Audience :: Developers
